push_queue/__init__.py
push_queue/custom_queue.py
push_queue/test.py
push_queue-1.1.0.dist-info/METADATA
push_queue-1.1.0.dist-info/WHEEL
push_queue-1.1.0.dist-info/top_level.txt
push_queue-1.1.0.dist-info/RECORD
