Metadata-Version: 2.1
Name: push-queue
Version: 1.1.0
Summary: A queue between thread with method push,drop old put into new
Home-page: https://github.com/mt6979/push_queue
Author: liuyancong
Author-email: 1437255447@qq.com
License: UNKNOWN
Platform: UNKNOWN
Classifier: Programming Language :: Python :: 3
Classifier: License :: OSI Approved :: MIT License
Classifier: Operating System :: OS Independent
Requires-Python: >=3.5
